{
	"Overview": [

	],
	"Purchase": [{
			"id": 1,
			"reward": "bravo-us",
			"reward_cat": "A",
			"quantity": 20,
			"purchase_date": "2019-11-01",
			"validity": "2020-04-30",
			"invoice_no": "RZYOU001"
		}, {
			"id": 2,
			"reward": "wow-us",
			"reward_cat": "B",
			"quantity": 20,
			"purchase_date": "2019-11-01",
			"validity": "2020-04-30",
			"invoice_no": "RZYOU002"
		},
		{
			"id": 3,
			"reward": "champ",
			"reward_cat": "C",
			"quantity": 10,
			"purchase_date": "2019-11-01",
			"validity": "2020-04-30",
			"invoice_no": "RZYOU003"
		}
	],
	"Allocation": [{
			"id": 20,
			"allocation_date": "2019-11-05",
			"purchase": {
				"id": 1,
				"reward": "bravo-us",
				"reward_cat": "A",
				"quantity": 20,
				"purchase_date": "2019-11-01",
				"validity": "2020-04-30",
				"invoice_no": "RZYOU001"
			},
			"quantity": 3
		},
		{
			"id": 21,
			"allocation_date": "2019-11-10",
			"purchase": {
				"id": 1,
				"reward": "bravo-us",
				"reward_cat": "A",
				"quantity": 20,
				"purchase_date": "2019-11-01",
				"validity": "2020-04-30",
				"invoice_no": "RZYOU001"
			},
			"quantity": 2
		},
		{
			"id": 22,
			"allocation_date": "2019-11-10",
			"purchase": {
				"id": 2,
				"reward": "wow-us",
				"reward_cat": "B",
				"quantity": 20,
				"purchase_date": "2019-11-01",
				"validity": "2020-04-30",
				"invoice_no": "RZYOU002"
			},
			"quantity": 4
		}, {
			"id": 23,
			"allocation_date": "2019-11-15",
			"purchase": {
				"id": 3,
				"reward": "champ",
				"reward_cat": "C",
				"quantity": 10,
				"purchase_date": "2019-11-01",
				"validity": "2020-04-30",
				"invoice_no": "RZYOU003"
			},
			"quantity": 1
		}
	],
	"Redemption": [{
			"resort_booking_id": "WBXSRO",
			"booking_date": "2019-11-11",
			"reward_cat": "A",
			"validity": "2020-04-30",
			"check_in_date": "2020-01-18",
			"reward": "bravo-us",
			"email": "john@you.com"
		},
		{
			"resort_booking_id": "ZBEHRU",
			"booking_date": "2019-11-11",
			"reward_cat": "A",
			"validity": "2020-04-30",
			"check_in_date": "2020-02-18",
			"reward": "bravo-us",
			"email": "abby@you.com"
		},
		{
			"resort_booking_id": "NPCUWS",
			"booking_date": "2019-11-12",
			"reward_cat": "B",
			"validity": "2020-04-30",
			"check_in_date": "2020-01-26",
			"reward": "wow-us",
			"email": "sara@you.com"
		},
		{
			"resort_booking_id": "CRUMSD",
			"booking_date": "2019-11-12",
			"reward_cat": "B",
			"validity": "2020-04-30",
			"check_in_date": "2020-02-01",
			"reward": "wow-us",
			"email": "jane@you.com"
		},
		{
			"resort_booking_id": "XUETQU",
			"booking_date": "2019-11-20",
			"reward_cat": "C",
			"validity": "2020-04-30",
			"check_in_date": "2020-02-15",
			"reward": "champ",
			"email": "dave@you.com"
		}
	]
}